{
  "reflection" : [
    {
      "condition" : {
        "typeReached" : "io.vertx.core.impl.resolver.DnsResolverProvider"
      },
      "type" : "com.sun.jndi.dns.DnsContextFactory"
    },
    {
      "condition" : {
        "typeReached" : "io.vertx.core.impl.resolver.DnsResolverProvider"
      },
      "type" : "io.netty.channel.AddressedEnvelope"
    },
    {
      "condition" : {
        "typeReached" : "io.vertx.core.impl.resolver.DnsResolverProvider"
      },
      "type" : "io.netty.channel.socket.DatagramPacket"
    },
    {
      "condition" : {
        "typeReached" : "io.vertx.core.impl.resolver.DnsResolverProvider"
      },
      "type" : "io.netty.handler.codec.dns.DnsQuery"
    },
    {
      "condition" : {
        "typeReached" : "io.vertx.core.impl.resolver.DnsResolverProvider"
      },
      "type" : "io.netty.resolver.dns.Cache$Entries"
    },
    {
      "condition" : {
        "typeReached" : "io.vertx.core.impl.transports.JDKTransport"
      },
      "type" : "io.netty.util.concurrent.DefaultPromise"
    },
    {
      "condition" : {
        "typeReached" : "io.vertx.core.impl.transports.JDKTransport"
      },
      "type" : "io.netty.util.concurrent.SingleThreadEventExecutor"
    },
    {
      "condition" : {
        "typeReached" : "io.vertx.core.impl.transports.JDKTransport"
      },
      "type" : "io.netty.util.internal.shaded.org.jctools.queues.BaseMpscLinkedArrayQueueColdProducerFields"
    },
    {
      "condition" : {
        "typeReached" : "io.vertx.core.impl.transports.JDKTransport"
      },
      "type" : "io.netty.util.internal.shaded.org.jctools.queues.BaseMpscLinkedArrayQueueConsumerFields"
    },
    {
      "condition" : {
        "typeReached" : "io.vertx.core.impl.transports.JDKTransport"
      },
      "type" : "io.netty.util.internal.shaded.org.jctools.queues.BaseMpscLinkedArrayQueueProducerFields"
    },
    {
      "condition" : {
        "typeReached" : "io.vertx.core.cli.converters.ConstructorBasedConverter"
      },
      "type" : "io.vertx.core.VertxException",
      "methods" : [
        {
          "name" : "<init>",
          "parameterTypes" : [
            "java.lang.String"
          ]
        }
      ]
    },
    {
      "condition" : {
        "typeReached" : "io.vertx.core.impl.launcher.commands.BareCommand"
      },
      "type" : "io.vertx.core.VertxOptions",
      "methods" : [
        {
          "name" : "setEventLoopPoolSize",
          "parameterTypes" : [
            "int"
          ]
        }
      ]
    },
    {
      "condition" : {
        "typeReached" : "io.vertx.core.impl.launcher.commands.BareCommand"
      },
      "type" : "io.vertx.core.eventbus.EventBusOptions"
    },
    {
      "condition" : {
        "typeReached" : "io.vertx.core.eventbus.impl.EventBusImpl"
      },
      "type" : "io.vertx.core.eventbus.impl.EventBusImpl"
    },
    {
      "condition" : {
        "typeReached" : "io.vertx.core.eventbus.impl.codecs.ClusterSerializableCodec"
      },
      "type" : "io.vertx.core.spi.cluster.RegistrationInfo",
      "methods" : [
        {
          "name" : "<init>",
          "parameterTypes" : [ ]
        }
      ]
    },
    {
      "condition" : {
        "typeReached" : "io.vertx.core.impl.ClusterSerializableUtils"
      },
      "type" : "io.vertx.core.spi.cluster.RegistrationInfo",
      "methods" : [
        {
          "name" : "<init>",
          "parameterTypes" : [ ]
        }
      ]
    },
    {
      "condition" : {
        "typeReached" : "io.vertx.core.impl.launcher.commands.ClasspathHandler"
      },
      "type" : "io.vertx.core.impl.launcher.commands.VertxIsolatedDeployer",
      "methods" : [
        {
          "name" : "<init>",
          "parameterTypes" : [ ]
        },
        {
          "name" : "deploy",
          "parameterTypes" : [
            "java.lang.String",
            "io.vertx.core.Vertx",
            "io.vertx.core.DeploymentOptions",
            "io.vertx.core.Handler"
          ]
        }
      ]
    },
    {
      "condition" : {
        "typeReached" : "io.vertx.core.logging.LoggerFactory"
      },
      "type" : "io.vertx.core.logging.Log4j2LogDelegateFactory",
      "methods" : [
        {
          "name" : "<init>",
          "parameterTypes" : [ ]
        }
      ]
    },
    {
      "condition" : {
        "typeReached" : "io.vertx.core.logging.LoggerFactory"
      },
      "type" : "io.vertx.core.logging.SLF4JLogDelegateFactory"
    },
    {
      "condition" : {
        "typeReached" : "io.vertx.core.impl.launcher.commands.BareCommand"
      },
      "type" : "io.vertx.core.net.TCPSSLOptions",
      "methods" : [
        {
          "name" : "setActivityLogDataFormat",
          "parameterTypes" : [
            "io.netty.handler.logging.ByteBufFormat"
          ]
        }
      ]
    },
    {
      "condition" : {
        "typeReached" : "io.vertx.core.logging.LoggerFactory"
      },
      "type" : "java.lang.StackTraceElement[]"
    },
    {
      "condition" : {
        "typeReached" : "io.vertx.core.impl.launcher.commands.BareCommand"
      },
      "type" : "java.lang.String[]"
    },
    {
      "condition" : {
        "typeReached" : "io.vertx.core.impl.launcher.commands.BareCommand"
      },
      "type" : "java.lang.reflect.Method[]"
    },
    {
      "condition" : {
        "typeReached" : "io.vertx.core.impl.resolver.DnsResolverProvider"
      },
      "type" : "java.net.InetAddress[]"
    },
    {
      "condition" : {
        "typeReached" : "io.vertx.core.impl.resolver.DnsResolverProvider"
      },
      "type" : "java.net.InetSocketAddress"
    },
    {
      "condition" : {
        "typeReached" : "io.vertx.core.impl.resolver.DnsResolverProvider"
      },
      "type" : "java.net.InterfaceAddress[]"
    },
    {
      "condition" : {
        "typeReached" : "io.vertx.core.impl.resolver.DnsResolverProvider"
      },
      "type" : "java.net.NetworkInterface[]"
    },
    {
      "condition" : {
        "typeReached" : "io.vertx.core.impl.Utils"
      },
      "type" : "java.nio.DirectByteBuffer"
    },
    {
      "condition" : {
        "typeReached" : "io.vertx.core.logging.JULLogDelegate"
      },
      "type" : "java.util.logging.ConsoleHandler"
    },
    {
      "condition" : {
        "typeReached" : "io.vertx.core.logging.JULLogDelegate"
      },
      "type" : "java.util.logging.Handler[]"
    },
    {
      "condition" : {
        "typeReached" : "io.vertx.core.logging.JULLogDelegate"
      },
      "type" : "java.util.logging.SimpleFormatter"
    },
    {
      "condition" : {
        "typeReached" : "io.vertx.core.impl.Utils"
      },
      "type" : "jdk.internal.misc.Unsafe"
    },
    {
      "condition" : {
        "typeReached" : "io.vertx.core.buffer.impl.VertxByteBufAllocator$1"
      },
      "type" : "io.netty.buffer.AbstractReferenceCountedByteBuf"
    },
    {
      "condition" : {
        "typeReached" : "io.vertx.core.impl.transports.JDKTransport"
      },
      "type" : "sun.nio.ch.SelectorImpl"
    },
    {
      "condition" : {
        "typeReached" : "io.vertx.core.file.impl.FileCache"
      },
      "type" : "sun.security.provider.NativePRNG"
    },
    {
      "condition" : {
        "typeReached" : "io.vertx.core.file.impl.FileCache"
      },
      "type" : "sun.security.provider.SHA"
    },
    {
      "condition" : {
        "typeReached" : "io.vertx.core.logging.JULLogDelegate"
      },
      "type" : "sun.util.logging.resources.logging"
    },
    {
      "condition" : {
        "typeReached" : "io.vertx.core.cli.annotations.CLIConfigurator"
      },
      "type" : {
        "proxy" : [
          "io.vertx.core.cli.annotations.Argument"
        ]
      }
    },
    {
      "condition" : {
        "typeReached" : "io.vertx.core.cli.annotations.CLIConfigurator"
      },
      "type" : {
        "proxy" : [
          "io.vertx.core.cli.annotations.Name"
        ]
      }
    },
    {
      "condition" : {
        "typeReached" : "io.vertx.core.cli.annotations.CLIConfigurator"
      },
      "type" : {
        "proxy" : [
          "io.vertx.core.cli.annotations.Option"
        ]
      }
    },
    {
      "condition" : {
        "typeReached" : "io.vertx.core.impl.Utils"
      },
      "type" : {
        "proxy" : [
          "java.lang.Deprecated"
        ]
      }
    },
    {
      "condition" : {
        "typeReached" : "io.vertx.core.cli.annotations.CLIConfigurator"
      },
      "type" : {
        "proxy" : [
          "java.lang.annotation.Retention"
        ]
      }
    },
    {
      "condition" : {
        "typeReached" : "io.vertx.core.impl.Utils"
      },
      "type" : {
        "proxy" : [
          "java.lang.annotation.Retention"
        ]
      }
    },
    {
      "condition" : {
        "typeReached" : "io.vertx.core.cli.converters.ConstructorBasedConverter"
      },
      "type" : "io.vertx.core.VertxException"
    },
    {
      "condition" : {
        "typeReached" : "io.vertx.core.impl.launcher.commands.ClasspathHandler"
      },
      "type" : "io.vertx.core.impl.launcher.commands.VertxIsolatedDeployer"
    },
    {
      "condition" : {
        "typeReached" : "io.vertx.core.logging.LoggerFactory"
      },
      "type" : "io.vertx.core.logging.Log4j2LogDelegateFactory"
    },
    {
      "condition" : {
        "typeReached" : "io.vertx.core.impl.SerializableUtils"
      },
      "type" : "java.lang.Object",
      "methods" : [
        {
          "name" : "<init>",
          "parameterTypes" : [ ]
        }
      ]
    },
    {
      "condition" : {
        "typeReached" : "io.vertx.core.impl.SerializableUtils"
      },
      "type" : "java.lang.String"
    },
    {
      "condition" : {
        "typeReached" : "io.vertx.core.impl.SerializableUtils"
      },
      "type" : "java.lang.reflect.Constructor[]"
    },
    {
      "condition" : {
        "typeReached" : "io.vertx.core.impl.SerializableUtils"
      },
      "type" : "java.lang.reflect.Field[]"
    },
    {
      "condition" : {
        "typeReached" : "io.vertx.core.impl.SerializableUtils"
      },
      "type" : "java.util.AbstractCollection"
    },
    {
      "condition" : {
        "typeReached" : "io.vertx.core.impl.SerializableUtils"
      },
      "type" : "java.util.CollSer",
      "serializable" : true
    },
    {
      "condition" : {
        "typeReached" : "io.vertx.core.impl.SerializableUtils"
      },
      "type" : "java.util.ImmutableCollections$AbstractImmutableCollection"
    },
    {
      "condition" : {
        "typeReached" : "io.vertx.core.impl.SerializableUtils"
      },
      "type" : "java.util.ImmutableCollections$AbstractImmutableList"
    },
    {
      "condition" : {
        "typeReached" : "io.vertx.core.impl.SerializableUtils"
      },
      "type" : "java.util.ImmutableCollections$List12",
      "serializable" : true
    }
  ],
  "serialization" : [
    {
      "condition" : {
        "typeReached" : "io.vertx.core.impl.SerializableUtils"
      },
      "type" : "java.lang.String"
    },
    {
      "condition" : {
        "typeReached" : "io.vertx.core.impl.SerializableUtils"
      },
      "type" : "java.util.CollSer"
    },
    {
      "condition" : {
        "typeReached" : "io.vertx.core.impl.SerializableUtils"
      },
      "type" : "java.util.ImmutableCollections$List12"
    }
  ],
  "resources" : [
    {
      "condition" : {
        "typeReached" : "io.vertx.core.ServiceHelper"
      },
      "glob" : "META-INF/services/io.vertx.core.spi.VerticleFactory"
    },
    {
      "condition" : {
        "typeReached" : "io.vertx.core.ServiceHelper"
      },
      "glob" : "META-INF/services/io.vertx.core.spi.VertxServiceProvider"
    },
    {
      "condition" : {
        "typeReached" : "io.vertx.core.impl.launcher.commands.VersionCommand"
      },
      "glob" : "META-INF/vertx/vertx-version.txt"
    },
    {
      "condition" : {
        "typeReached" : "io.vertx.core.impl.resolver.DnsResolverProvider"
      },
      "glob" : "jndi.properties"
    },
    {
      "condition" : {
        "typeReached" : "io.vertx.core.logging.LoggerFactory"
      },
      "glob" : "vertx-default-jul-logging.properties"
    },
    {
      "condition" : {
        "typeReached" : "io.vertx.core.logging.JULLogDelegate"
      },
      "module" : "java.logging",
      "glob" : "sun/util/logging/resources/logging_en.properties"
    },
    {
      "condition" : {
        "typeReached" : "io.vertx.core.logging.JULLogDelegate"
      },
      "module" : "java.logging",
      "glob" : "sun/util/logging/resources/logging_en_US.properties"
    }
  ]
}
