[
  {
    "latest" : true,
    "metadata-version" : "2.11.8",
    "source-code-url" : "https://repo.maven.apache.org/maven2/org/scala-lang/scala-library/$version$/scala-library-$version$-sources.jar",
    "repository-url" : "https://github.com/scala/scala",
    "test-code-url" : "https://github.com/scala/scala/tree/v$version$/test",
    "documentation-url" : "https://repo.maven.apache.org/maven2/org/scala-lang/scala-library/$version$/scala-library-$version$-javadoc.jar",
    "description" : "Scala Library is the standard runtime library for the Scala programming language on the JVM. It provides core language support, collections, concurrency utilities, and other foundational APIs required by Scala programs.",
    "language" : {
      "name" : "scala",
      "version" : "2"
    },
    "tested-versions" : [
      "2.11.8"
    ],
    "allowed-packages" : [
      "scala"
    ]
  }
]
