{
  "buildArgs": ["-verbose", "-Ob", "-H:+ReportExceptionStackTraces"],
  "generateMatrixBatchedCoordinates": {
    "java": ["21", "25", "latest-ea"],
    "os": ["ubuntu-latest"]
  },
  "generateChangedCoordinatesMatrix": {
    "java": ["21", "25", "latest-ea"],
    "os": ["ubuntu-latest"]
  },
  "generateInfrastructureChangedCoordinatesMatrix": {
    "java": ["21", "25", "latest-ea"],
    "os": ["ubuntu-latest"]
  },
  "generateMatrixMatchingCoordinates": {
    "java": ["21", "25","latest-ea"],
    "os": ["ubuntu-latest"]
  }
}
