[
  {
    "latest" : true,
    "metadata-version" : "2.0.0-M15",
    "source-code-url" : "https://repo.maven.apache.org/maven2/org/apache/directory/server/apacheds-i18n/$version$/apacheds-i18n-$version$-sources.jar",
    "repository-url" : "https://svn.apache.org/repos/asf/directory/apacheds",
    "test-code-url" : "N/A",
    "documentation-url" : "https://repo.maven.apache.org/maven2/org/apache/directory/server/apacheds-i18n/$version$/apacheds-i18n-$version$-javadoc.jar",
    "description" : "ApacheDS I18n provides the internationalization message bundle used by Apache Directory Server for localized errors and other messages. It exposes Java constants and resource bundles for server messages, including default, German, and French translations in the org.apache.directory.server.i18n package.",
    "tested-versions" : [
      "2.0.0.AM25",
      "2.0.0.AM26",
      "2.0.0.AM27",
      "2.0.0-M15",
      "2.0.0-M16",
      "2.0.0-M17",
      "2.0.0-M18",
      "2.0.0-M19",
      "2.0.0-M20",
      "2.0.0-M21",
      "2.0.0-M22",
      "2.0.0-M23",
      "2.0.0-M24"
    ],
    "allowed-packages" : [
      "org.apache.directory.server.i18n"
    ]
  }
]
