{
  "reflection" : [
    {
      "condition" : {
        "typeReached" : "akka.actor.typed.ActorSystem$"
      },
      "type" : "akka.actor.ActorSystemImpl",
      "fields" : [
        {
          "name" : "0bitmap$1"
        }
      ]
    },
    {
      "condition" : {
        "typeReached" : "akka.actor.typed.internal.adapter.PropsAdapter$"
      },
      "type" : "akka.actor.Props$EmptyActor",
      "methods" : [
        {
          "name" : "<init>",
          "parameterTypes" : [ ]
        }
      ]
    },
    {
      "condition" : {
        "typeReached" : "akka.actor.ActorSystem$Settings$"
      },
      "type" : "akka.event.slf4j.Slf4jLogger"
    },
    {
      "condition" : {
        "typeReached" : "akka.event.EventStream"
      },
      "type" : "akka.event.EventStream",
      "fields" : [
        {
          "name" : "0bitmap$1"
        }
      ]
    },
    {
      "condition" : {
        "typeReached" : "akka.actor.Address"
      },
      "type" : "akka.actor.Address",
      "fields" : [
        {
          "name" : "0bitmap$1"
        }
      ]
    },
    {
      "condition" : {
        "typeReached" : "akka.actor.ActorSystemImpl"
      },
      "type" : "akka.event.slf4j.Slf4jLoggingFilter",
      "methods" : [
        {
          "name" : "<init>",
          "parameterTypes" : [
            "akka.actor.ActorSystem$Settings",
            "akka.event.EventStream"
          ]
        }
      ]
    },
    {
      "condition" : {
        "typeReached" : "akka.actor.ActorSystemImpl"
      },
      "type" : "akka.actor.LocalActorRefProvider",
      "fields" : [
        {
          "name" : "0bitmap$1"
        }
      ],
      "methods" : [
        {
          "name" : "<init>",
          "parameterTypes" : [
            "java.lang.String",
            "akka.actor.ActorSystem$Settings",
            "akka.event.EventStream",
            "akka.actor.DynamicAccess"
          ]
        }
      ]
    },
    {
      "condition" : {
        "typeReached" : "akka.actor.ActorSystemImpl"
      },
      "type" : "akka.actor.DefaultSupervisorStrategy",
      "methods" : [
        {
          "name" : "<init>",
          "parameterTypes" : [ ]
        }
      ]
    },
    {
      "condition" : {
        "typeReached" : "akka.actor.Deployer"
      },
      "type" : "akka.routing.NoRouter",
      "methods" : [
        {
          "name" : "<init>",
          "parameterTypes" : [ ]
        }
      ]
    },
    {
      "condition" : {
        "typeReached" : "akka.actor.Deployer"
      },
      "type" : "akka.routing.RoundRobinPool",
      "methods" : [
        {
          "name" : "<init>",
          "parameterTypes" : [
            "com.typesafe.config.Config"
          ]
        }
      ]
    },
    {
      "condition" : {
        "typeReached" : "akka.actor.Deployer"
      },
      "type" : "akka.routing.RoundRobinGroup",
      "methods" : [
        {
          "name" : "<init>",
          "parameterTypes" : [
            "com.typesafe.config.Config"
          ]
        }
      ]
    },
    {
      "condition" : {
        "typeReached" : "akka.actor.Deployer"
      },
      "type" : "akka.routing.RandomPool",
      "methods" : [
        {
          "name" : "<init>",
          "parameterTypes" : [
            "com.typesafe.config.Config"
          ]
        }
      ]
    },
    {
      "condition" : {
        "typeReached" : "akka.actor.Deployer"
      },
      "type" : "akka.routing.RandomGroup",
      "methods" : [
        {
          "name" : "<init>",
          "parameterTypes" : [
            "com.typesafe.config.Config"
          ]
        }
      ]
    },
    {
      "condition" : {
        "typeReached" : "akka.actor.Deployer"
      },
      "type" : "akka.routing.BalancingPool",
      "methods" : [
        {
          "name" : "<init>",
          "parameterTypes" : [
            "com.typesafe.config.Config"
          ]
        }
      ]
    },
    {
      "condition" : {
        "typeReached" : "akka.actor.Deployer"
      },
      "type" : "akka.routing.SmallestMailboxPool",
      "methods" : [
        {
          "name" : "<init>",
          "parameterTypes" : [
            "com.typesafe.config.Config"
          ]
        }
      ]
    },
    {
      "condition" : {
        "typeReached" : "akka.actor.Deployer"
      },
      "type" : "akka.routing.BroadcastPool",
      "methods" : [
        {
          "name" : "<init>",
          "parameterTypes" : [
            "com.typesafe.config.Config"
          ]
        }
      ]
    },
    {
      "condition" : {
        "typeReached" : "akka.actor.Deployer"
      },
      "type" : "akka.routing.BroadcastGroup",
      "methods" : [
        {
          "name" : "<init>",
          "parameterTypes" : [
            "com.typesafe.config.Config"
          ]
        }
      ]
    },
    {
      "condition" : {
        "typeReached" : "akka.actor.Deployer"
      },
      "type" : "akka.routing.ScatterGatherFirstCompletedPool",
      "methods" : [
        {
          "name" : "<init>",
          "parameterTypes" : [
            "com.typesafe.config.Config"
          ]
        }
      ]
    },
    {
      "condition" : {
        "typeReached" : "akka.actor.Deployer"
      },
      "type" : "akka.routing.ScatterGatherFirstCompletedGroup",
      "methods" : [
        {
          "name" : "<init>",
          "parameterTypes" : [
            "com.typesafe.config.Config"
          ]
        }
      ]
    },
    {
      "condition" : {
        "typeReached" : "akka.actor.Deployer"
      },
      "type" : "akka.routing.TailChoppingPool",
      "methods" : [
        {
          "name" : "<init>",
          "parameterTypes" : [
            "com.typesafe.config.Config"
          ]
        }
      ]
    },
    {
      "condition" : {
        "typeReached" : "akka.actor.Deployer"
      },
      "type" : "akka.routing.TailChoppingGroup",
      "methods" : [
        {
          "name" : "<init>",
          "parameterTypes" : [
            "com.typesafe.config.Config"
          ]
        }
      ]
    },
    {
      "condition" : {
        "typeReached" : "akka.actor.Deployer"
      },
      "type" : "akka.routing.ConsistentHashingPool",
      "methods" : [
        {
          "name" : "<init>",
          "parameterTypes" : [
            "com.typesafe.config.Config"
          ]
        }
      ]
    },
    {
      "condition" : {
        "typeReached" : "akka.actor.Deployer"
      },
      "type" : "akka.routing.ConsistentHashingGroup",
      "methods" : [
        {
          "name" : "<init>",
          "parameterTypes" : [
            "com.typesafe.config.Config"
          ]
        }
      ]
    },
    {
      "condition" : {
        "typeReached" : "akka.actor.ActorSystemImpl"
      },
      "type" : "akka.actor.LightArrayRevolverScheduler",
      "methods" : [
        {
          "name" : "<init>",
          "parameterTypes" : [
            "com.typesafe.config.Config",
            "akka.event.LoggingAdapter",
            "java.util.concurrent.ThreadFactory"
          ]
        }
      ]
    }
  ],
  "resources" : [
    {
      "glob" : "application.conf"
    },
    {
      "glob" : "application.json"
    },
    {
      "glob" : "application.properties"
    },
    {
      "glob" : "reference.conf"
    },
    {
      "glob" : "reference.json"
    },
    {
      "glob" : "reference.properties"
    },
    {
      "glob" : "version.conf"
    },
    {
      "glob" : "version.json"
    },
    {
      "glob" : "version.properties"
    }
  ]
}
