[
  {
    "latest" : true,
    "metadata-version" : "1.7",
    "source-code-url" : "https://repo.maven.apache.org/maven2/org/sonatype/aether/aether-impl/$version$/aether-impl-$version$-sources.jar",
    "repository-url" : "https://github.com/sonatype/sonatype-aether",
    "test-code-url" : "https://repo.maven.apache.org/maven2/org/sonatype/aether/aether-parent/$version$/aether-parent-$version$-source-release.zip",
    "documentation-url" : "https://repo.maven.apache.org/maven2/org/sonatype/aether/aether-impl/$version$/aether-impl-$version$-javadoc.jar",
    "description" : "Aether Implementation provides the default services that implement Sonatype Aether's repository system. It handles dependency collection and resolution, artifact and metadata installation and deployment, repository management, and service location for applications using Aether.",
    "tested-versions" : [
      "1.7"
    ],
    "allowed-packages" : [
      "org.sonatype.aether.impl"
    ]
  }
]
