{
  "badges" : {
    "dynamicAccessCoverage" : "30.5%",
    "librariesSupported" : "501",
    "testedLibraryVersions" : "6,585",
    "testedLinesOfCode" : "1,199,094"
  },
  "date" : "2026-05-02",
  "metrics" : {
    "metadataIndexes" : {
      "latestEntries" : 501,
      "metadataBaselines" : 700,
      "metadataIndexes" : 501,
      "testedVersions" : 6585
    },
    "stats" : {
      "coverageStatsArtifacts" : 497,
      "dynamicAccessCallCoveragePercent" : 30.5,
      "testedLinesOfCode" : 1199094
    }
  }
}
