[
  {
    "latest" : true,
    "metadata-version" : "8.0.3",
    "source-code-url" : "https://repo1.maven.org/maven2/com/itextpdf/forms/8.0.3/forms-8.0.3-sources.jar",
    "repository-url" : "https://github.com/itext/itext-java",
    "test-code-url" : "https://github.com/itext/itext-java/tree/8.0.3/forms/src/test",
    "documentation-url" : "https://repo1.maven.org/maven2/com/itextpdf/forms/8.0.3/forms-8.0.3-javadoc.jar",
    "description" : "The iText forms module provides APIs for creating, reading, and modifying interactive PDF forms and their fields. It supports AcroForm and XFA processing, including field value updates, annotations, and form flattening.",
    "tested-versions" : [
      "8.0.3",
      "8.0.4",
      "8.0.5",
      "9.0.0",
      "9.1.0",
      "9.2.0",
      "9.3.0",
      "9.4.0",
      "9.5.0",
      "9.6.0"
    ],
    "allowed-packages" : [
      "com.itextpdf"
    ]
  }
]
