[
  {
    "latest" : true,
    "metadata-version" : "0.1.0",
    "source-code-url" : "https://repo.maven.apache.org/maven2/com/ibm/async/asyncutil/0.1.0/asyncutil-0.1.0-sources.jar",
    "repository-url" : "https://github.com/IBM/java-async-util",
    "test-code-url" : "https://github.com/IBM/java-async-util/tree/v0.1.0/asyncutil/src/test",
    "documentation-url" : "https://repo.maven.apache.org/maven2/com/ibm/async/asyncutil/0.1.0/asyncutil-0.1.0-javadoc.jar",
    "description" : "AsyncUtil provides Java utilities for composing and coordinating CompletionStage-based asynchronous workflows. It includes helpers for async iteration, locks, queues, and stage collection so applications can build non-blocking control flow on top of CompletableFuture.",
    "tested-versions" : [
      "0.1.0"
    ],
    "allowed-packages" : [
      "com.ibm.asyncutil"
    ]
  }
]
