[
  {
    "latest" : true,
    "metadata-version" : "4.0.24",
    "source-code-url" : "https://repo.maven.apache.org/maven2/org/apache/groovy/groovy-sql/$version$/groovy-sql-$version$-sources.jar",
    "repository-url" : "https://github.com/apache/groovy",
    "test-code-url" : "https://archive.apache.org/dist/groovy/$version$/sources/apache-groovy-src-$version$.zip",
    "documentation-url" : "https://docs.groovy-lang.org/docs/groovy-$version$/html/documentation/sql-userguide.html",
    "description" : "Apache Groovy SQL adds the groovy.sql API for working with relational databases through JDBC from Groovy code. It provides conveniences for executing queries and updates, parameter binding, result-set handling, batching, transactions, and DataSet-style data access.",
    "language" : {
      "name" : "groovy",
      "version" : "4.0"
    },
    "tested-versions" : [
      "4.0.24"
    ],
    "allowed-packages" : [
      "groovy.sql",
      "org.apache.groovy.sql.extensions"
    ]
  }
]
