{
  "reflection" : [
    {
      "condition" : {
        "typeReached" : "org.apache.hadoop.conf.Configuration"
      },
      "type" : "com.sun.org.apache.xerces.internal.jaxp.DocumentBuilderFactoryImpl",
      "methods" : [
        {
          "name" : "<init>",
          "parameterTypes" : [ ]
        }
      ]
    },
    {
      "condition" : {
        "typeReached" : "org.apache.hadoop.conf.Configuration"
      },
      "type" : "java.lang.String"
    },
    {
      "condition" : {
        "typeReached" : "org.apache.hadoop.conf.Configuration"
      },
      "type" : "java.lang.Thread",
      "methods" : [
        {
          "name" : "getContextClassLoader",
          "parameterTypes" : [ ]
        }
      ]
    },
    {
      "condition" : {
        "typeReached" : "org.apache.hadoop.conf.Configuration"
      },
      "type" : "org.apache.commons.logging.LogFactory"
    },
    {
      "condition" : {
        "typeReached" : "org.apache.hadoop.conf.Configuration"
      },
      "type" : "org.apache.commons.logging.impl.Log4JLogger",
      "methods" : [
        {
          "name" : "<init>",
          "parameterTypes" : [
            "java.lang.String"
          ]
        }
      ]
    },
    {
      "condition" : {
        "typeReached" : "org.apache.hadoop.yarn.server.security.http.RMAuthenticationFilterInitializer"
      },
      "type" : "org.apache.commons.logging.impl.Log4JLogger",
      "methods" : [
        {
          "name" : "<init>",
          "parameterTypes" : [
            "java.lang.String"
          ]
        }
      ]
    },
    {
      "condition" : {
        "typeReached" : "org.apache.hadoop.yarn.server.sharedcache.SharedCacheUtil"
      },
      "type" : "org.apache.commons.logging.impl.Log4JLogger",
      "methods" : [
        {
          "name" : "<init>",
          "parameterTypes" : [
            "java.lang.String"
          ]
        }
      ]
    },
    {
      "condition" : {
        "typeReached" : "org.apache.hadoop.conf.Configuration"
      },
      "type" : "org.apache.commons.logging.impl.LogFactoryImpl",
      "methods" : [
        {
          "name" : "<init>",
          "parameterTypes" : [ ]
        }
      ]
    },
    {
      "condition" : {
        "typeReached" : "org.apache.hadoop.conf.Configuration"
      },
      "type" : "org.apache.commons.logging.impl.WeakHashtable",
      "methods" : [
        {
          "name" : "<init>",
          "parameterTypes" : [ ]
        }
      ]
    },
    {
      "condition" : {
        "typeReached" : "org.apache.hadoop.yarn.api.records.ApplicationAttemptId"
      },
      "type" : "org.apache.hadoop.yarn.api.records.impl.pb.ApplicationAttemptIdPBImpl",
      "methods" : [
        {
          "name" : "<init>",
          "parameterTypes" : [ ]
        }
      ]
    },
    {
      "condition" : {
        "typeReached" : "org.apache.hadoop.yarn.api.records.ApplicationId"
      },
      "type" : "org.apache.hadoop.yarn.api.records.impl.pb.ApplicationIdPBImpl",
      "methods" : [
        {
          "name" : "<init>",
          "parameterTypes" : [ ]
        }
      ]
    },
    {
      "condition" : {
        "typeReached" : "org.apache.hadoop.yarn.api.records.ContainerId"
      },
      "type" : "org.apache.hadoop.yarn.api.records.impl.pb.ContainerIdPBImpl",
      "methods" : [
        {
          "name" : "<init>",
          "parameterTypes" : [ ]
        }
      ]
    },
    {
      "condition" : {
        "typeReached" : "org.apache.hadoop.yarn.server.utils.BuilderUtils"
      },
      "type" : "org.apache.hadoop.yarn.api.records.impl.pb.ContainerPBImpl",
      "methods" : [
        {
          "name" : "<init>",
          "parameterTypes" : [ ]
        }
      ]
    },
    {
      "condition" : {
        "typeReached" : "org.apache.hadoop.yarn.server.utils.BuilderUtils"
      },
      "type" : "org.apache.hadoop.yarn.api.records.impl.pb.ContainerStatusPBImpl",
      "methods" : [
        {
          "name" : "<init>",
          "parameterTypes" : [ ]
        }
      ]
    },
    {
      "condition" : {
        "typeReached" : "org.apache.hadoop.yarn.server.utils.BuilderUtils"
      },
      "type" : "org.apache.hadoop.yarn.api.records.impl.pb.LocalResourcePBImpl",
      "methods" : [
        {
          "name" : "<init>",
          "parameterTypes" : [ ]
        }
      ]
    },
    {
      "condition" : {
        "typeReached" : "org.apache.hadoop.yarn.api.records.NodeId"
      },
      "type" : "org.apache.hadoop.yarn.api.records.impl.pb.NodeIdPBImpl",
      "methods" : [
        {
          "name" : "<init>",
          "parameterTypes" : [ ]
        }
      ]
    },
    {
      "condition" : {
        "typeReached" : "org.apache.hadoop.yarn.api.records.Priority"
      },
      "type" : "org.apache.hadoop.yarn.api.records.impl.pb.PriorityPBImpl",
      "methods" : [
        {
          "name" : "<init>",
          "parameterTypes" : [ ]
        }
      ]
    },
    {
      "condition" : {
        "typeReached" : "org.apache.hadoop.yarn.api.records.Resource"
      },
      "type" : "org.apache.hadoop.yarn.api.records.impl.pb.ResourcePBImpl",
      "methods" : [
        {
          "name" : "<init>",
          "parameterTypes" : [ ]
        }
      ]
    },
    {
      "condition" : {
        "typeReached" : "org.apache.hadoop.yarn.server.utils.BuilderUtils"
      },
      "type" : "org.apache.hadoop.yarn.api.records.impl.pb.ResourceRequestPBImpl",
      "methods" : [
        {
          "name" : "<init>",
          "parameterTypes" : [ ]
        }
      ]
    },
    {
      "condition" : {
        "typeReached" : "org.apache.hadoop.yarn.api.records.ResourceUtilization"
      },
      "type" : "org.apache.hadoop.yarn.api.records.impl.pb.ResourceUtilizationPBImpl",
      "methods" : [
        {
          "name" : "<init>",
          "parameterTypes" : [ ]
        }
      ]
    },
    {
      "condition" : {
        "typeReached" : "org.apache.hadoop.yarn.server.utils.BuilderUtils"
      },
      "type" : "org.apache.hadoop.yarn.api.records.impl.pb.TokenPBImpl",
      "methods" : [
        {
          "name" : "<init>",
          "parameterTypes" : [ ]
        }
      ]
    },
    {
      "condition" : {
        "typeReached" : "org.apache.hadoop.yarn.api.records.URL"
      },
      "type" : "org.apache.hadoop.yarn.api.records.impl.pb.URLPBImpl",
      "methods" : [
        {
          "name" : "<init>",
          "parameterTypes" : [ ]
        }
      ]
    },
    {
      "condition" : {
        "typeReached" : "org.apache.hadoop.yarn.server.utils.BuilderUtils"
      },
      "type" : "org.apache.hadoop.yarn.api.records.impl.pb.URLPBImpl",
      "methods" : [
        {
          "name" : "<init>",
          "parameterTypes" : [ ]
        }
      ]
    },
    {
      "condition" : {
        "typeReached" : "org.apache.hadoop.yarn.factory.providers.RecordFactoryProvider"
      },
      "type" : "org.apache.hadoop.yarn.factories.impl.pb.RecordFactoryPBImpl",
      "methods" : [
        {
          "name" : "get",
          "parameterTypes" : [ ]
        }
      ]
    },
    {
      "condition" : {
        "typeReached" : "org.apache.hadoop.conf.Configuration"
      },
      "type" : "org.apache.log4j.Category"
    },
    {
      "condition" : {
        "typeReached" : "org.apache.hadoop.conf.Configuration"
      },
      "type" : "org.apache.log4j.CategoryKey"
    },
    {
      "condition" : {
        "typeReached" : "org.apache.hadoop.conf.Configuration"
      },
      "type" : "org.apache.log4j.Level",
      "fields" : [
        {
          "name" : "TRACE"
        }
      ]
    },
    {
      "condition" : {
        "typeReached" : "org.apache.hadoop.conf.Configuration"
      },
      "type" : "org.apache.log4j.Logger"
    },
    {
      "condition" : {
        "typeReached" : "org.apache.hadoop.conf.Configuration"
      },
      "type" : "org.apache.log4j.Priority"
    },
    {
      "condition" : {
        "typeReached" : "org.apache.hadoop.conf.Configuration"
      },
      "type" : "org.apache.log4j.helpers.Loader"
    }
  ],
  "resources" : [
    {
      "condition" : {
        "typeReached" : "org.apache.hadoop.conf.Configuration"
      },
      "glob" : "META-INF/services/javax.xml.parsers.DocumentBuilderFactory"
    },
    {
      "condition" : {
        "typeReached" : "org.apache.hadoop.conf.Configuration"
      },
      "glob" : "META-INF/services/org.apache.commons.logging.LogFactory"
    },
    {
      "condition" : {
        "typeReached" : "org.apache.hadoop.conf.Configuration"
      },
      "glob" : "commons-logging.properties"
    },
    {
      "condition" : {
        "typeReached" : "org.apache.hadoop.conf.Configuration"
      },
      "glob" : "core-default.xml"
    },
    {
      "condition" : {
        "typeReached" : "org.apache.hadoop.conf.Configuration"
      },
      "glob" : "core-site.xml"
    },
    {
      "condition" : {
        "typeReached" : "org.apache.hadoop.conf.Configuration"
      },
      "glob" : "hadoop-site.xml"
    },
    {
      "condition" : {
        "typeReached" : "org.apache.hadoop.conf.Configuration"
      },
      "glob" : "log4j.properties"
    },
    {
      "condition" : {
        "typeReached" : "org.apache.hadoop.conf.Configuration"
      },
      "glob" : "log4j.xml"
    },
    {
      "condition" : {
        "typeReached" : "org.apache.hadoop.conf.Configuration"
      },
      "glob" : "org/slf4j/impl/StaticLoggerBinder.class"
    }
  ]
}
