[
  {
    "latest" : true,
    "metadata-version" : "2.8.1",
    "source-code-url" : "https://repo1.maven.org/maven2/org/playframework/anorm/anorm_3/$version$/anorm_3-$version$-sources.jar",
    "repository-url" : "https://github.com/playframework/anorm",
    "test-code-url" : "https://github.com/playframework/anorm/tree/$version$/core/src/test",
    "documentation-url" : "https://repo1.maven.org/maven2/org/playframework/anorm/anorm_3/$version$/anorm_3-$version$-javadoc.jar",
    "description" : "Anorm is a Scala data access library that uses plain SQL over JDBC to interact with relational databases. It provides APIs for binding query parameters and parsing result sets into Scala data structures without acting as an object-relational mapper.",
    "language" : {
      "name" : "scala",
      "version" : "3"
    },
    "tested-versions" : [
      "2.8.1"
    ],
    "allowed-packages" : [
      "anorm",
      "com.github.ghik.silencer",
      "org.joda",
      "resource",
      "scala"
    ]
  }
]
